swmfpy/__init__.py
swmfpy/io.py
swmfpy/paramin.py
swmfpy/tecplottools.py
swmfpy/tools.py
swmfpy/web.py
swmfpy-2024.1.dist-info/LICENSE
swmfpy-2024.1.dist-info/METADATA
swmfpy-2024.1.dist-info/WHEEL
swmfpy-2024.1.dist-info/top_level.txt
swmfpy-2024.1.dist-info/RECORD
