Metadata-Version: 2.1
Name: swmfpy
Version: 2024.1
Summary: A collection of tools for the Space Weather Modelling
Home-page: https://gitlab.umich.edu/swmf_software/swmfpy
Author: Qusai Al Shidi
Author-email: qusai@umich.edu
License: LGPLv3
Classifier: Programming Language :: Python :: 3
Classifier: License :: OSI Approved :: GNU Lesser General Public License v3 (LGPLv3)
Classifier: Operating System :: OS Independent
Classifier: Intended Audience :: Science/Research
Classifier: Topic :: Scientific/Engineering :: Astronomy
Classifier: Topic :: Scientific/Engineering :: Physics
Classifier: Topic :: Scientific/Engineering :: Visualization
Requires-Python: >=3.6
License-File: LICENSE
Requires-Dist: python-dateutil
Requires-Dist: numpy
Requires-Dist: filecache
Provides-Extra: hmi
Requires-Dist: drms ; extra == 'hmi'
Provides-Extra: tecplottools
Requires-Dist: h5py ; extra == 'tecplottools'
